BioClients/__init__.py
BioClients/allen/__init__.py
BioClients/allen/brain/Client.py
BioClients/allen/brain/Utils.py
BioClients/allen/brain/__init__.py
BioClients/amp/__init__.py
BioClients/amp/t2d/Client.py
BioClients/amp/t2d/Utils.py
BioClients/amp/t2d/__init__.py
BioClients/badapple/Client.py
BioClients/badapple/Utils.py
BioClients/badapple/__init__.py
BioClients/bindingdb/Client.py
BioClients/bindingdb/Utils.py
BioClients/bindingdb/__init__.py
BioClients/biogrid/Client.py
BioClients/biogrid/Utils.py
BioClients/biogrid/__init__.py
BioClients/biomarkerkb/Client.py
BioClients/biomarkerkb/Utils.py
BioClients/biomarkerkb/__init__.py
BioClients/bioregistry/Client.py
BioClients/bioregistry/Utils.py
BioClients/bioregistry/__init__.py
BioClients/brenda/Client.py
BioClients/brenda/Utils.py
BioClients/brenda/__init__.py
BioClients/cas/Client.py
BioClients/cas/Utils.py
BioClients/cas/__init__.py
BioClients/cdc/Client.py
BioClients/cdc/Utils.py
BioClients/cdc/__init__.py
BioClients/cfde/__init__.py
BioClients/cfde/cfchemdb/Client.py
BioClients/cfde/cfchemdb/Utils.py
BioClients/cfde/cfchemdb/__init__.py
BioClients/chebi/Client.py
BioClients/chebi/Utils.py
BioClients/chebi/__init__.py
BioClients/chem2bio2rdf/Client.py
BioClients/chem2bio2rdf/Utils.py
BioClients/chem2bio2rdf/__init__.py
BioClients/chem2bio2rdf/slap/Client.py
BioClients/chem2bio2rdf/slap/Utils.py
BioClients/chem2bio2rdf/slap/__init__.py
BioClients/chembl/Client.py
BioClients/chembl/FetchByID.py
BioClients/chembl/UnichemClient.py
BioClients/chembl/Utils.py
BioClients/chembl/__init__.py
BioClients/chemidplus/Client.py
BioClients/chemidplus/Utils.py
BioClients/chemidplus/__init__.py
BioClients/clinicaltrials/Client.py
BioClients/clinicaltrials/Utils.py
BioClients/clinicaltrials/__init__.py
BioClients/disgenet/Client.py
BioClients/disgenet/Utils.py
BioClients/disgenet/__init__.py
BioClients/dnorm/Client.py
BioClients/dnorm/__init__.py
BioClients/drugcentral/Client.py
BioClients/drugcentral/Test.py
BioClients-0.2.30.dist-info/LICENSE
BioClients-0.2.30.dist-info/METADATA
BioClients-0.2.30.dist-info/WHEEL
BioClients-0.2.30.dist-info/top_level.txt
BioClients-0.2.30.dist-info/RECORD
