Metadata-Version: 2.1
Name: BioClients
Version: 0.2.30
Summary: Clients for online biomedical resources, usually via REST APIs.
Home-page: https://github.com/jeremyjyang/BioClients
Author: Jeremy Yang
Author-email: jeremyjyang@gmail.com
Classifier: Programming Language :: Python :: 3
Classifier: License :: OSI Approved :: MIT License
Classifier: Operating System :: OS Independent
Requires-Python: >=3.10
License-File: LICENSE
